ftp2webdav/__init__.py
ftp2webdav/cli.py
ftp2webdav/config.py
ftp2webdav/resources/example-config.yml
ftp2webdav/server.py
ftp2webdav-0.1.dist-info/METADATA
ftp2webdav-0.1.dist-info/WHEEL
ftp2webdav-0.1.dist-info/entry_points.txt
ftp2webdav-0.1.dist-info/RECORD
