Metadata-Version: 2.1
Name: ftp2webdav
Version: 0.1
Summary: An FTP server that forwards uploaded files to a WebDAV server
License: MIT
Author: Tomas Bayer
Author-email: mail@tomas.berlin
Requires-Python: >=3.9,<4.0
Classifier: License :: OSI Approved :: MIT License
Classifier: Programming Language :: Python :: 3
Classifier: Programming Language :: Python :: 3.9
Classifier: Programming Language :: Python :: 3.10
Classifier: Programming Language :: Python :: 3.11
Classifier: Programming Language :: Python :: 3.12
Requires-Dist: cerberus (>=1.3.4,<2.0.0)
Requires-Dist: easywebdav (>=1.2.0,<2.0.0)
Requires-Dist: ftprelay (>=0.1,<0.2)
Requires-Dist: pyyaml (>=6.0,<7.0)
Requires-Dist: typer[all] (>=0.9.0,<0.10.0)
